atlo/__init__.py
atlo/cli.py
atlo/config.py
atlo/detector.py
atlo/diff.py
atlo/export.py
atlo/init_template.py
atlo/logs.py
atlo/multi_runner.py
atlo/parser.py
atlo/progress.py
atlo/utils.py
atlo/workflow.py
atlo_cli-0.1.0.dist-info/licenses/LICENSE
atlo_cli-0.1.0.dist-info/METADATA
atlo_cli-0.1.0.dist-info/WHEEL
atlo_cli-0.1.0.dist-info/entry_points.txt
atlo_cli-0.1.0.dist-info/top_level.txt
atlo_cli-0.1.0.dist-info/RECORD
