Metadata-Version: 2.4
Name: atlo-cli
Version: 0.1.0
Summary: Run Atlantis workflows locally - Local Terraform plan execution with parallel support, smart filtering, and beautiful output
Author-email: Jon Savage <jonwsavage@users.noreply.github.com>
License: MIT
Project-URL: Homepage, https://github.com/jonwsavage/atlo
Project-URL: Issues, https://github.com/jonwsavage/atlo/issues
Project-URL: PyPI, https://pypi.org/project/atlo-cli/
Keywords: terraform,atlantis,infrastructure,devops,automation,ci-cd,iac,terraform-plan,terraform-automation,infrastructure-as-code
Classifier: Development Status :: 4 - Beta
Classifier: Intended Audience :: Developers
Classifier: Intended Audience :: System Administrators
Classifier: License :: OSI Approved :: MIT License
Classifier: Operating System :: OS Independent
Classifier: Programming Language :: Python :: 3
Classifier: Programming Language :: Python :: 3.8
Classifier: Programming Language :: Python :: 3.9
Classifier: Programming Language :: Python :: 3.10
Classifier: Programming Language :: Python :: 3.11
Classifier: Programming Language :: Python :: 3.12
Classifier: Topic :: Software Development :: Build Tools
Classifier: Topic :: System :: Systems Administration
Classifier: Topic :: Utilities
Classifier: Environment :: Console
Classifier: Typing :: Typed
Requires-Python: >=3.8
License-File: LICENSE
Requires-Dist: typer>=0.9.0
Requires-Dist: pyyaml>=6.0
Requires-Dist: rich>=13.0.0
Provides-Extra: dev
Requires-Dist: pytest>=7.0.0; extra == "dev"
Requires-Dist: pytest-cov>=4.0.0; extra == "dev"
Requires-Dist: ruff>=0.1.0; extra == "dev"
Requires-Dist: black>=23.0.0; extra == "dev"
Dynamic: license-file
